{
  "id": 3488,
  "schema": "genepedia/person@1",
  "slug": "johanna-fredrica-de-beer",
  "names": {
    "display": "Johanna Fredrica de Beer",
    "given": "Johanna Fredrica",
    "surname": "de Beer",
    "married": "Van Jaarsveld",
    "nick": "a2b6c13d3",
    "aliases": []
  },
  "sex": "female",
  "living": false,
  "events": {
    "birth": {
      "date": "5 JUL 1797",
      "year": 1797,
      "iso": "1797-07-05",
      "precision": "exact",
      "display": "July 5, 1797",
      "place": "Graaff-Reinet, Eastern Cape, South Africa",
      "location": {
        "label": "Graaff-Reinet, Eastern Cape, South Africa",
        "placeName": "",
        "addressLine1": "",
        "addressLine2": "",
        "addressLine3": "",
        "city": "Graaff-Reinet",
        "postalCode": "",
        "county": "",
        "stateProvince": "Eastern Cape",
        "country": "South Africa",
        "countryCode": "",
        "latitude": "",
        "longitude": "",
        "source": ""
      }
    },
    "death": {
      "date": "ABT 1897",
      "year": 1897,
      "iso": "1897",
      "precision": "about",
      "display": "about 1897",
      "place": null
    },
    "baptism": {
      "date": "3 DEC 1797",
      "year": 1797,
      "iso": "1797-12-03",
      "precision": "exact",
      "display": "December 3, 1797",
      "place": "Graaff-Reinet, Eastern Cape, South Africa",
      "location": {
        "label": "Graaff-Reinet, Eastern Cape, South Africa",
        "placeName": "",
        "addressLine1": "",
        "addressLine2": "",
        "addressLine3": "",
        "city": "Graaff-Reinet",
        "postalCode": "",
        "county": "",
        "stateProvince": "Eastern Cape",
        "country": "South Africa",
        "countryCode": "",
        "latitude": "",
        "longitude": "",
        "source": ""
      }
    },
    "burial": null
  },
  "lastResidence": null,
  "lastResidenceLocation": null,
  "occupation": null,
  "attributes": {
    "hairColor": null,
    "eyeColor": null,
    "height": null,
    "weight": null,
    "ethnicity": null,
    "religion": null,
    "politicalViews": null,
    "languages": [],
    "hobbies": [],
    "shoeSize": null,
    "smoking": null
  },
  "media": {
    "primary": null,
    "items": []
  },
  "about": {
    "hasNarrative": false
  },
  "relationships": {
    "parents": [
      3484,
      3485
    ],
    "spouses": [],
    "exSpouses": [],
    "children": [],
    "siblings": [
      3486,
      3487,
      3489,
      3490,
      3491,
      3492,
      3493,
      3494,
      3495,
      1385,
      3496
    ],
    "parentUnions": [
      "F857"
    ],
    "spouseUnions": [],
    "parentLinks": [
      {
        "id": 3484,
        "unionId": "F857",
        "type": "biological"
      },
      {
        "id": 3485,
        "unionId": "F857",
        "type": "biological"
      }
    ],
    "partnerLinks": [],
    "childLinks": []
  },
  "source": {
    "gedcomXref": "@I6000000016030841277@",
    "geniId": "6000000016030841277",
    "rfn": "geni:6000000016030841277",
    "changed": "20 MAY 2025"
  },
  "page": {
    "route": "pages/people/3488/",
    "canonical": "https://www.genepedia.org/pages/people/3488/"
  },
  "generatedAt": "2026-06-15T17:28:05.203Z"
}
