{
  "id": 3855,
  "schema": "genepedia/person@1",
  "slug": "james-swan-germishuizen",
  "names": {
    "display": "James Swan Germishuizen",
    "given": "James Swan",
    "surname": "Germishuizen",
    "married": "",
    "nick": "",
    "aliases": []
  },
  "sex": "male",
  "living": false,
  "events": {
    "birth": {
      "date": "19 MAY 1918",
      "year": 1918,
      "iso": "1918-05-19",
      "precision": "exact",
      "display": "May 19, 1918",
      "place": null
    },
    "death": null,
    "baptism": null,
    "burial": null
  },
  "lastResidence": null,
  "lastResidenceLocation": null,
  "occupation": null,
  "attributes": {
    "hairColor": null,
    "eyeColor": null,
    "height": null,
    "weight": null,
    "ethnicity": null,
    "religion": null,
    "politicalViews": null,
    "languages": [],
    "hobbies": [],
    "shoeSize": null,
    "smoking": null
  },
  "media": {
    "primary": null,
    "items": []
  },
  "about": {
    "hasNarrative": false
  },
  "relationships": {
    "parents": [
      1521,
      3851
    ],
    "spouses": [],
    "exSpouses": [],
    "children": [],
    "siblings": [
      3852,
      3853,
      3854,
      3856,
      3857,
      3858
    ],
    "parentUnions": [
      "F916"
    ],
    "spouseUnions": [],
    "parentLinks": [
      {
        "id": 1521,
        "unionId": "F916",
        "type": "biological"
      },
      {
        "id": 3851,
        "unionId": "F916",
        "type": "biological"
      }
    ],
    "partnerLinks": [],
    "childLinks": []
  },
  "source": {
    "gedcomXref": "@I6000000171829224535@",
    "geniId": "6000000171829224535",
    "rfn": "geni:6000000171829224535",
    "changed": "25 JAN 2021"
  },
  "page": {
    "route": "people/3855/",
    "canonical": "https://www.genepedia.org/people/3855/"
  },
  "generatedAt": "2026-06-15T17:28:05.206Z"
}
