{
  "id": 4538,
  "schema": "genepedia/person@1",
  "slug": "phyllis-bertha-slater",
  "names": {
    "display": "Phyllis Bertha Slater",
    "given": "Phyllis Bertha",
    "surname": "Van Zyl",
    "married": "Slater",
    "nick": "",
    "aliases": []
  },
  "sex": "female",
  "living": true,
  "events": {
    "birth": {
      "date": "13 OCT 1950",
      "year": 1950,
      "iso": "1950-10-13",
      "precision": "exact",
      "display": "October 13, 1950",
      "place": null
    },
    "death": null,
    "baptism": null,
    "burial": null
  },
  "lastResidence": null,
  "lastResidenceLocation": null,
  "occupation": null,
  "attributes": {
    "hairColor": null,
    "eyeColor": null,
    "height": null,
    "weight": null,
    "ethnicity": null,
    "religion": null,
    "politicalViews": null,
    "languages": [],
    "hobbies": [],
    "shoeSize": null,
    "smoking": null
  },
  "media": {
    "primary": {
      "local": null,
      "remote": "https://media.geni.com/p14/62/21/6b/a5/534448663b4fefcd/screenshot_2024-07-20_234833_original.jpg?hash=329a598e5aac8ea078dac8c8d78f1e100438a5a796378ddb7f29fecd5517a0b9.1789455599",
      "alt": "Phyllis Bertha Slater"
    },
    "items": [
      {
        "remote": "https://media.geni.com/p14/62/21/6b/a5/534448663b4fefcd/screenshot_2024-07-20_234833_original.jpg?hash=329a598e5aac8ea078dac8c8d78f1e100438a5a796378ddb7f29fecd5517a0b9.1789455599",
        "form": "",
        "title": "",
        "primary": true,
        "local": null
      }
    ]
  },
  "about": {
    "hasNarrative": false
  },
  "relationships": {
    "parents": [
      1784,
      4537
    ],
    "spouses": [],
    "exSpouses": [],
    "children": [],
    "siblings": [
      4539,
      4540,
      4541
    ],
    "parentUnions": [
      "F1081"
    ],
    "spouseUnions": [],
    "parentLinks": [
      {
        "id": 1784,
        "unionId": "F1081",
        "type": "biological"
      },
      {
        "id": 4537,
        "unionId": "F1081",
        "type": "biological"
      }
    ],
    "partnerLinks": [],
    "childLinks": []
  },
  "source": {
    "gedcomXref": "@I6000000204898503831@",
    "geniId": "6000000204898503831",
    "rfn": "geni:6000000204898503831",
    "changed": "21 JUL 2024"
  },
  "page": {
    "route": "pages/people/4538/",
    "canonical": "https://www.genepedia.org/pages/people/4538/"
  },
  "generatedAt": "2026-06-15T17:28:05.212Z"
}
