{
  "id": 4895,
  "schema": "genepedia/person@1",
  "slug": "engela-maria-gertruida-bernardo",
  "names": {
    "display": "Engela Maria Gertruida Bernardo",
    "given": "Engela Maria Gertruida",
    "surname": "Bester",
    "married": "Bernardo",
    "nick": "",
    "aliases": [
      "Engela Maria Gertruida Bernardo"
    ]
  },
  "sex": "female",
  "living": true,
  "events": {
    "birth": {
      "date": "20 MAR 1952",
      "year": 1952,
      "iso": "1952-03-20",
      "precision": "exact",
      "display": "March 20, 1952",
      "place": "Pretoria, Gauteng, South Africa",
      "location": {
        "label": "Pretoria, Gauteng, South Africa",
        "placeName": "",
        "addressLine1": "",
        "addressLine2": "",
        "addressLine3": "",
        "city": "Pretoria",
        "postalCode": "",
        "county": "",
        "stateProvince": "Gauteng",
        "country": "South Africa",
        "countryCode": "",
        "latitude": "",
        "longitude": "",
        "source": ""
      }
    },
    "death": null,
    "baptism": null,
    "burial": null
  },
  "lastResidence": null,
  "lastResidenceLocation": null,
  "occupation": null,
  "attributes": {
    "hairColor": null,
    "eyeColor": null,
    "height": null,
    "weight": null,
    "ethnicity": null,
    "religion": null,
    "politicalViews": null,
    "languages": [],
    "hobbies": [],
    "shoeSize": null,
    "smoking": null
  },
  "media": {
    "primary": null,
    "items": []
  },
  "about": {
    "hasNarrative": false
  },
  "relationships": {
    "parents": [
      1912,
      4892
    ],
    "spouses": [],
    "exSpouses": [],
    "children": [],
    "siblings": [
      4893,
      4894,
      4896,
      4897,
      4898
    ],
    "parentUnions": [
      "F1163"
    ],
    "spouseUnions": [],
    "parentLinks": [
      {
        "id": 1912,
        "unionId": "F1163",
        "type": "biological"
      },
      {
        "id": 4892,
        "unionId": "F1163",
        "type": "biological"
      }
    ],
    "partnerLinks": [],
    "childLinks": []
  },
  "source": {
    "gedcomXref": "@I6000000066678119905@",
    "geniId": "6000000066678119905",
    "rfn": "geni:6000000066678119905",
    "changed": "07 JUL 2022"
  },
  "page": {
    "route": "pages/people/4895/",
    "canonical": "https://www.genepedia.org/pages/people/4895/"
  },
  "generatedAt": "2026-06-15T17:28:05.215Z"
}
