{
  "id": 264,
  "schema": "genepedia/person@1",
  "slug": "darren-edwards",
  "names": {
    "display": "Darren Edwards",
    "given": "Darren",
    "surname": "Edwards",
    "married": "Edwards",
    "nick": "",
    "aliases": []
  },
  "sex": "male",
  "living": true,
  "events": {
    "birth": null,
    "death": null,
    "baptism": null,
    "burial": null
  },
  "lastResidence": null,
  "lastResidenceLocation": null,
  "occupation": null,
  "attributes": {
    "hairColor": null,
    "eyeColor": null,
    "height": null,
    "weight": null,
    "ethnicity": null,
    "religion": null,
    "politicalViews": null,
    "languages": [],
    "hobbies": [],
    "shoeSize": null,
    "smoking": null
  },
  "media": {
    "primary": null,
    "items": []
  },
  "about": {
    "hasNarrative": false
  },
  "relationships": {
    "parents": [
      99
    ],
    "spouses": [],
    "exSpouses": [],
    "children": [],
    "siblings": [
      262,
      263
    ],
    "parentUnions": [
      "F84"
    ],
    "spouseUnions": [],
    "parentLinks": [
      {
        "id": 99,
        "unionId": "F84",
        "type": "biological"
      }
    ],
    "partnerLinks": [],
    "childLinks": []
  },
  "source": {
    "gedcomXref": "@I6000000204069435833@",
    "geniId": "6000000204069435833",
    "rfn": "geni:6000000204069435833",
    "changed": "13 MAR 2024"
  },
  "page": {
    "route": "people/264/",
    "canonical": "https://www.genepedia.org/people/264/"
  },
  "generatedAt": "2026-06-15T17:28:05.176Z"
}
