{
  "key": "ek",
  "count": 6,
  "persons": [
    {
      "id": 2790,
      "name": "Jan Johan Ekhard Davids",
      "given": "Jan Johan Ekhard",
      "surname": "Davids",
      "birthYear": 1864,
      "deathYear": 1898,
      "slug": "jan-johan-ekhard-davids",
      "route": "pages/people/2790/",
      "hasImage": true
    },
    {
      "id": 1835,
      "name": "? Eksteen",
      "given": "?",
      "surname": "Eksteen",
      "birthYear": null,
      "deathYear": null,
      "slug": "eksteen",
      "route": "pages/people/1835/",
      "hasImage": false
    },
    {
      "id": 1836,
      "name": "? Day",
      "given": "?",
      "surname": "Eksteen",
      "birthYear": null,
      "deathYear": null,
      "slug": "day",
      "route": "pages/people/1836/",
      "hasImage": false
    },
    {
      "id": 1837,
      "name": "? Eksteen",
      "given": "?",
      "surname": "Eksteen",
      "birthYear": null,
      "deathYear": null,
      "slug": "eksteen-1837",
      "route": "pages/people/1837/",
      "hasImage": false
    },
    {
      "id": 797,
      "name": "Barbara Louise Ellis",
      "given": "Barbara Louise",
      "surname": "Ellis",
      "birthYear": null,
      "deathYear": null,
      "slug": "barbara-louise-ellis",
      "route": "pages/people/797/",
      "hasImage": true
    },
    {
      "id": 4289,
      "name": "Martha Johanna Jacomina Griesel",
      "given": "Martha Johanna Jacomina",
      "surname": "Griesel",
      "birthYear": 1881,
      "deathYear": null,
      "slug": "martha-johanna-jacomina-griesel",
      "route": "pages/people/4289/",
      "hasImage": true
    }
  ]
}
