{
  "key": "sp",
  "count": 4,
  "persons": [
    {
      "id": 4572,
      "name": "Anna Maria Spies",
      "given": "Anna Maria",
      "surname": "Spies",
      "birthYear": 1763,
      "deathYear": 1840,
      "slug": "anna-maria-spies",
      "route": "pages/people/4572/",
      "hasImage": false
    },
    {
      "id": 3313,
      "name": "Junita Claudina van der Spuy",
      "given": "Junita Claudina",
      "surname": "van der Spuy",
      "birthYear": 1903,
      "deathYear": 1974,
      "slug": "junita-claudina-van-der-spuy",
      "route": "pages/people/3313/",
      "hasImage": true
    },
    {
      "id": 3320,
      "name": "Jan Sybrand van der Spuy van Taak",
      "given": "Jan Sybrand van der Spuy",
      "surname": "van Taak",
      "birthYear": 1942,
      "deathYear": 2016,
      "slug": "jan-sybrand-van-der-spuy-van-taak",
      "route": "pages/people/3320/",
      "hasImage": true
    },
    {
      "id": 3221,
      "name": "Johannes Petrus Spangenberg Van Zyl",
      "given": "Johannes Petrus Spangenberg",
      "surname": "Van Zyl",
      "birthYear": 1870,
      "deathYear": null,
      "slug": "johannes-petrus-spangenberg-van-zyl",
      "route": "pages/people/3221/",
      "hasImage": false
    }
  ]
}
