{
  "id": "F285",
  "schema": "genepedia/union@1",
  "partners": [
    1060,
    1059
  ],
  "children": [
    1061,
    1062,
    1063,
    1064,
    429,
    429
  ],
  "events": {
    "engagement": null,
    "marriage": {
      "date": "7 APR 1816",
      "year": 1816,
      "iso": "1816-04-07",
      "precision": "exact",
      "display": "April 7, 1816",
      "place": "George, Western Cape, South Africa",
      "location": {
        "label": "George, Western Cape, South Africa",
        "placeName": "",
        "addressLine1": "",
        "addressLine2": "",
        "addressLine3": "",
        "city": "George",
        "postalCode": "",
        "county": "",
        "stateProvince": "Western Cape",
        "country": "South Africa",
        "countryCode": "",
        "latitude": "",
        "longitude": "",
        "source": ""
      }
    },
    "divorce": null
  },
  "source": {
    "gedcomXref": "@F6000000023047948975@"
  }
}
