{
  "id": 2178,
  "schema": "genepedia/person@1",
  "slug": "john-gotlieb-sinden-2178",
  "names": {
    "display": "John Gotlieb Sinden",
    "given": "John Gotlieb",
    "surname": "Sinden",
    "married": "Sinden",
    "nick": "Jn Gotlieb Sinden",
    "aliases": []
  },
  "sex": "male",
  "living": false,
  "events": {
    "birth": {
      "date": "8 FEB 1897",
      "year": 1897,
      "iso": "1897-02-08",
      "precision": "exact",
      "display": "February 8, 1897",
      "place": "Griekwastad",
      "location": {
        "label": "Griekwastad",
        "placeName": "",
        "addressLine1": "",
        "addressLine2": "",
        "addressLine3": "",
        "city": "Griekwastad",
        "postalCode": "",
        "county": "",
        "stateProvince": "",
        "country": "",
        "countryCode": "",
        "latitude": "",
        "longitude": "",
        "source": ""
      }
    },
    "death": {
      "date": "7 OCT 1984",
      "year": 1984,
      "iso": "1984-10-07",
      "precision": "exact",
      "display": "October 7, 1984",
      "place": "Brits, South Africa",
      "location": {
        "label": "Brits, South Africa",
        "placeName": "",
        "addressLine1": "",
        "addressLine2": "",
        "addressLine3": "",
        "city": "Brits",
        "postalCode": "",
        "county": "",
        "stateProvince": "",
        "country": "South Africa",
        "countryCode": "",
        "latitude": "",
        "longitude": "",
        "source": ""
      }
    },
    "baptism": {
      "date": "23 FEB 1897",
      "year": 1897,
      "iso": "1897-02-23",
      "precision": "exact",
      "display": "February 23, 1897",
      "place": "Griekwastad, Northern Cape, South Africa",
      "location": {
        "label": "Griekwastad, Northern Cape, South Africa",
        "placeName": "",
        "addressLine1": "",
        "addressLine2": "",
        "addressLine3": "",
        "city": "Griekwastad",
        "postalCode": "",
        "county": "",
        "stateProvince": "Northern Cape",
        "country": "South Africa",
        "countryCode": "",
        "latitude": "",
        "longitude": "",
        "source": ""
      }
    },
    "burial": {
      "date": "9 OCT 1984",
      "year": 1984,
      "iso": "1984-10-09",
      "precision": "exact",
      "display": "October 9, 1984",
      "place": "Langberg, Brits, South Africa",
      "location": {
        "label": "Langberg, Brits, South Africa",
        "placeName": "Langberg",
        "addressLine1": "",
        "addressLine2": "",
        "addressLine3": "",
        "city": "Brits",
        "postalCode": "",
        "county": "",
        "stateProvince": "",
        "country": "South Africa",
        "countryCode": "",
        "latitude": "",
        "longitude": "",
        "source": ""
      },
      "type": "burial"
    }
  },
  "lastResidence": null,
  "lastResidenceLocation": null,
  "occupation": null,
  "attributes": {
    "hairColor": null,
    "eyeColor": null,
    "height": null,
    "weight": null,
    "ethnicity": null,
    "religion": null,
    "politicalViews": null,
    "languages": [],
    "hobbies": [],
    "shoeSize": null,
    "smoking": null
  },
  "media": {
    "primary": {
      "local": null,
      "remote": "https://media.geni.com/p13/6a/87/99/78/5344483de61308c8/sinden-jan-gotlieb-1897-1984_original.jpg?hash=bb0c62c1088d77463e5e964b350f111aee15eef04ddb394523dfd24902ae9157.1789455599",
      "alt": "John Gotlieb Sinden"
    },
    "items": [
      {
        "remote": "https://media.geni.com/p13/6a/87/99/78/5344483de61308c8/sinden-jan-gotlieb-1897-1984_original.jpg?hash=bb0c62c1088d77463e5e964b350f111aee15eef04ddb394523dfd24902ae9157.1789455599",
        "form": "",
        "title": "",
        "primary": true,
        "local": null
      },
      {
        "remote": "https://media.geni.com/p13/3a/06/7c/3f/5344483fa580da56/record-image_3qsq-g9s9-hb3m_original.jpg?hash=2b0a054e217eba128f588b100ecfb70b73a3f46cfdcb31935b12d4b0fcb81967.1789455599",
        "form": "",
        "title": "record-image_trou 1925  jpg",
        "primary": false,
        "local": null
      },
      {
        "remote": "https://media.geni.com/p13/b2/2f/e8/7a/5344485f371af500/record-image_1__original.jpg?hash=0b51af3325eeba24d74234ed2064acc119ea49153cf1a7c2ab3ebe22e40ec68f.1789455599",
        "form": "",
        "title": "record-image_ trou 1925.jpg",
        "primary": false,
        "local": null
      },
      {
        "remote": "https://media.geni.com/p14/3d/32/c1/4f/53444866509971f5/image_1__original.jpg?hash=e13df24eaf11fb9bc29c0b4dcd6cd4973404c023693b20c478a1962069dc749e.1789455599",
        "form": "",
        "title": "record-image_doop .jpg",
        "primary": false,
        "local": null
      }
    ]
  },
  "about": {
    "hasNarrative": false
  },
  "relationships": {
    "parents": [
      895,
      2173
    ],
    "spouses": [],
    "exSpouses": [],
    "children": [],
    "siblings": [
      2174,
      2175,
      2176,
      2177,
      2179,
      2180,
      2181,
      2182,
      2183,
      2184,
      2185
    ],
    "parentUnions": [
      "F557"
    ],
    "spouseUnions": [
      "F1339"
    ],
    "parentLinks": [
      {
        "id": 895,
        "unionId": "F557",
        "type": "biological"
      },
      {
        "id": 2173,
        "unionId": "F557",
        "type": "biological"
      }
    ],
    "partnerLinks": [],
    "childLinks": []
  },
  "source": {
    "gedcomXref": "@I6000000028409803943@",
    "geniId": "6000000028409803943",
    "rfn": "geni:6000000028409803943",
    "changed": "03 AUG 2024"
  },
  "page": {
    "route": "people/2178/",
    "canonical": "https://www.genepedia.org/people/2178/"
  },
  "generatedAt": "2026-06-15T17:28:05.189Z"
}
