{
  "id": 2392,
  "schema": "genepedia/person@1",
  "slug": "alida-petronella-cloete-2392",
  "names": {
    "display": "Alida Petronella Cloete",
    "given": "Alida Petronella",
    "surname": "Cloete",
    "married": "",
    "nick": "",
    "aliases": []
  },
  "sex": "female",
  "living": false,
  "events": {
    "birth": {
      "date": "21 MAR 1900",
      "year": 1900,
      "iso": "1900-03-21",
      "precision": "exact",
      "display": "March 21, 1900",
      "place": "Griekwastad, Northern Cape, South Africa",
      "location": {
        "label": "Griekwastad, Northern Cape, South Africa",
        "placeName": "",
        "addressLine1": "",
        "addressLine2": "",
        "addressLine3": "",
        "city": "Griekwastad",
        "postalCode": "",
        "county": "",
        "stateProvince": "Northern Cape",
        "country": "South Africa",
        "countryCode": "",
        "latitude": "",
        "longitude": "",
        "source": ""
      }
    },
    "death": {
      "date": "8 JUL 1901",
      "year": 1901,
      "iso": "1901-07-08",
      "precision": "exact",
      "display": "July 8, 1901",
      "place": null
    },
    "baptism": {
      "date": "11 NOV 1900",
      "year": 1900,
      "iso": "1900-11-11",
      "precision": "exact",
      "display": "November 11, 1900",
      "place": "Griekwastad, Northern Cape, South Africa",
      "location": {
        "label": "Griekwastad, Northern Cape, South Africa",
        "placeName": "",
        "addressLine1": "",
        "addressLine2": "",
        "addressLine3": "",
        "city": "Griekwastad",
        "postalCode": "",
        "county": "",
        "stateProvince": "Northern Cape",
        "country": "South Africa",
        "countryCode": "",
        "latitude": "",
        "longitude": "",
        "source": ""
      }
    },
    "burial": null
  },
  "lastResidence": null,
  "lastResidenceLocation": null,
  "occupation": null,
  "attributes": {
    "hairColor": null,
    "eyeColor": null,
    "height": null,
    "weight": null,
    "ethnicity": null,
    "religion": null,
    "politicalViews": null,
    "languages": [],
    "hobbies": [],
    "shoeSize": null,
    "smoking": null
  },
  "media": {
    "primary": {
      "local": null,
      "remote": "https://media.geni.com/p14/41/b6/2c/16/5344486169e8172d/died_young_original.jpg?hash=f2169abce4d735f249bf7bb7abcc733a78d0c9865c353df36385df26a5a58296.1789455599",
      "alt": "Alida Petronella Cloete"
    },
    "items": [
      {
        "remote": "https://media.geni.com/p14/41/b6/2c/16/5344486169e8172d/died_young_original.jpg?hash=f2169abce4d735f249bf7bb7abcc733a78d0c9865c353df36385df26a5a58296.1789455599",
        "form": "",
        "title": "",
        "primary": true,
        "local": null
      },
      {
        "remote": "https://media.geni.com/p14/a7/d6/f3/1f/534448616704c591/alida_petronella_cloete_baptism_11_nov_1900_griekwastad_original.jpg?hash=66ac2ef2a361c84e64640574d3dcf9e46721885b9b19e4f341fb90cb305c647e.1789455599",
        "form": "",
        "title": "Alida Petronella Cloete Baptism 11 Nov 1900 Griekwastad.jpg",
        "primary": false,
        "local": null
      }
    ]
  },
  "about": {
    "hasNarrative": false
  },
  "relationships": {
    "parents": [
      958,
      2387
    ],
    "spouses": [],
    "exSpouses": [],
    "children": [],
    "siblings": [
      2388,
      2389,
      2390,
      2391,
      2393,
      2394,
      2395,
      2396
    ],
    "parentUnions": [
      "F603"
    ],
    "spouseUnions": [],
    "parentLinks": [
      {
        "id": 958,
        "unionId": "F603",
        "type": "biological"
      },
      {
        "id": 2387,
        "unionId": "F603",
        "type": "biological"
      }
    ],
    "partnerLinks": [],
    "childLinks": []
  },
  "source": {
    "gedcomXref": "@I6000000134959216873@",
    "geniId": "6000000134959216873",
    "rfn": "geni:6000000134959216873",
    "changed": "27 AUG 2022"
  },
  "page": {
    "route": "people/2392/",
    "canonical": "https://www.genepedia.org/people/2392/"
  },
  "generatedAt": "2026-06-15T17:28:05.189Z"
}
