{
  "id": 2444,
  "schema": "genepedia/person@1",
  "slug": "frans-jacobus-jooste",
  "names": {
    "display": "Frans Jacobus Jooste",
    "given": "Frans Jacobus",
    "surname": "Jooste",
    "married": "Jooste",
    "nick": "",
    "aliases": []
  },
  "sex": "male",
  "living": false,
  "events": {
    "birth": {
      "date": "9 SEP 1810",
      "year": 1810,
      "iso": "1810-09-09",
      "precision": "exact",
      "display": "September 9, 1810",
      "place": "Tulbagh, Western Cape, South Africa",
      "location": {
        "label": "Tulbagh, Western Cape, South Africa",
        "placeName": "",
        "addressLine1": "",
        "addressLine2": "",
        "addressLine3": "",
        "city": "Tulbagh",
        "postalCode": "",
        "county": "",
        "stateProvince": "Western Cape",
        "country": "South Africa",
        "countryCode": "",
        "latitude": "",
        "longitude": "",
        "source": ""
      }
    },
    "death": {
      "date": "8 AUG 1843",
      "year": 1843,
      "iso": "1843-08-08",
      "precision": "exact",
      "display": "August 8, 1843",
      "place": null
    },
    "baptism": {
      "date": "2 DEC 1810",
      "year": 1810,
      "iso": "1810-12-02",
      "precision": "exact",
      "display": "December 2, 1810",
      "place": "Tulbagh, Western Cape, South Africa",
      "location": {
        "label": "Tulbagh, Western Cape, South Africa",
        "placeName": "",
        "addressLine1": "",
        "addressLine2": "",
        "addressLine3": "",
        "city": "Tulbagh",
        "postalCode": "",
        "county": "",
        "stateProvince": "Western Cape",
        "country": "South Africa",
        "countryCode": "",
        "latitude": "",
        "longitude": "",
        "source": ""
      }
    },
    "burial": null
  },
  "lastResidence": null,
  "lastResidenceLocation": null,
  "occupation": null,
  "attributes": {
    "hairColor": null,
    "eyeColor": null,
    "height": null,
    "weight": null,
    "ethnicity": null,
    "religion": null,
    "politicalViews": null,
    "languages": [],
    "hobbies": [],
    "shoeSize": null,
    "smoking": null
  },
  "media": {
    "primary": {
      "local": null,
      "remote": "https://media.geni.com/p13/82/a7/4d/a2/5344483d9f70333a/tulbagh_baptism_2_dec_1810_frans_jacobus_jooste_original.jpg?hash=2e3ca4653054d17a505083c3ef9cdd5ea6064399820ac9830455df541b518c60.1789455599",
      "alt": "Frans Jacobus Jooste"
    },
    "items": [
      {
        "remote": "https://media.geni.com/p13/82/a7/4d/a2/5344483d9f70333a/tulbagh_baptism_2_dec_1810_frans_jacobus_jooste_original.jpg?hash=2e3ca4653054d17a505083c3ef9cdd5ea6064399820ac9830455df541b518c60.1789455599",
        "form": "",
        "title": "Tulbagh Baptism 2 Dec 1810 Frans Jacobus Jooste",
        "primary": true,
        "local": null
      },
      {
        "remote": "https://media.geni.com/p13/ee/5f/9d/e5/5344483dd64bf523/tulbagh_baptism_14_jul_1841_jacobus_francois_johannes_jooste_crop_original.jpg?hash=c52a0494daaf604fe990f76ce052dd92a2eaa0a66803d2b0cc16b63ca8fa67a6.1789455599",
        "form": "",
        "title": "Tulbagh Baptism 14 Jul 1841 Jacobus Francois Johannes Jooste",
        "primary": false,
        "local": null
      }
    ]
  },
  "about": {
    "hasNarrative": false
  },
  "relationships": {
    "parents": [
      2438,
      2437
    ],
    "spouses": [],
    "exSpouses": [],
    "children": [],
    "siblings": [
      2439,
      2440,
      2441,
      2442,
      2443,
      2445,
      2446,
      1000
    ],
    "parentUnions": [
      "F615"
    ],
    "spouseUnions": [
      "F1491",
      "F1492"
    ],
    "parentLinks": [
      {
        "id": 2438,
        "unionId": "F615",
        "type": "biological"
      },
      {
        "id": 2437,
        "unionId": "F615",
        "type": "biological"
      }
    ],
    "partnerLinks": [],
    "childLinks": []
  },
  "source": {
    "gedcomXref": "@I6000000021725420635@",
    "geniId": "6000000021725420635",
    "rfn": "geni:6000000021725420635",
    "changed": "20 MAY 2025"
  },
  "page": {
    "route": "people/2444/",
    "canonical": "https://www.genepedia.org/people/2444/"
  },
  "generatedAt": "2026-06-15T17:28:05.190Z"
}
