{
  "id": 2669,
  "schema": "genepedia/person@1",
  "slug": "theunis-johannes-kotze-2669",
  "names": {
    "display": "Theunis Johannes Kotze",
    "given": "Theunis Johannes",
    "surname": "Kotze",
    "married": "Kotze",
    "nick": "Kotzé",
    "aliases": []
  },
  "sex": "male",
  "living": false,
  "events": {
    "birth": {
      "date": "24 SEP 1842",
      "year": 1842,
      "iso": "1842-09-24",
      "precision": "exact",
      "display": "September 24, 1842",
      "place": "South Africa",
      "location": {
        "label": "South Africa",
        "placeName": "South Africa",
        "addressLine1": "",
        "addressLine2": "",
        "addressLine3": "",
        "city": "",
        "postalCode": "",
        "county": "",
        "stateProvince": "",
        "country": "",
        "countryCode": "",
        "latitude": "",
        "longitude": "",
        "source": ""
      }
    },
    "death": {
      "date": "22 JUN 1898",
      "year": 1898,
      "iso": "1898-06-22",
      "precision": "exact",
      "display": "June 22, 1898",
      "place": "South Africa",
      "location": {
        "label": "South Africa",
        "placeName": "South Africa",
        "addressLine1": "",
        "addressLine2": "",
        "addressLine3": "",
        "city": "",
        "postalCode": "",
        "county": "",
        "stateProvince": "",
        "country": "",
        "countryCode": "",
        "latitude": "",
        "longitude": "",
        "source": ""
      }
    },
    "baptism": null,
    "burial": null
  },
  "lastResidence": null,
  "lastResidenceLocation": null,
  "occupation": null,
  "attributes": {
    "hairColor": null,
    "eyeColor": null,
    "height": null,
    "weight": null,
    "ethnicity": null,
    "religion": null,
    "politicalViews": null,
    "languages": [],
    "hobbies": [],
    "shoeSize": null,
    "smoking": null
  },
  "media": {
    "primary": {
      "local": null,
      "remote": "https://www.geni.com/images/documents/doc.png",
      "alt": "Theunis Johannes Kotze"
    },
    "items": [
      {
        "remote": "https://www.geni.com/images/documents/doc.png",
        "form": "",
        "title": "Ancestry Family Trees",
        "primary": true,
        "local": null
      }
    ]
  },
  "about": {
    "hasNarrative": true
  },
  "relationships": {
    "parents": [
      2667,
      2666
    ],
    "spouses": [],
    "exSpouses": [],
    "children": [],
    "siblings": [
      2668,
      2670,
      1075,
      2671,
      2672,
      2673,
      2674
    ],
    "parentUnions": [
      "F654"
    ],
    "spouseUnions": [
      "F1649"
    ],
    "parentLinks": [
      {
        "id": 2667,
        "unionId": "F654",
        "type": "biological"
      },
      {
        "id": 2666,
        "unionId": "F654",
        "type": "biological"
      }
    ],
    "partnerLinks": [],
    "childLinks": []
  },
  "source": {
    "gedcomXref": "@I6000000021686508943@",
    "geniId": "6000000021686508943",
    "rfn": "geni:6000000021686508943",
    "changed": "28 APR 2022"
  },
  "page": {
    "route": "people/2669/",
    "canonical": "https://www.genepedia.org/people/2669/"
  },
  "generatedAt": "2026-06-15T17:28:05.191Z"
}
